storageprovider/__init__.py
storageprovider/client.py
tests/__init__.py
tests/test_client.py
storageprovider_client-2.6.0.dist-info/LICENSE
storageprovider_client-2.6.0.dist-info/METADATA
storageprovider_client-2.6.0.dist-info/WHEEL
storageprovider_client-2.6.0.dist-info/entry_points.txt
storageprovider_client-2.6.0.dist-info/top_level.txt
storageprovider_client-2.6.0.dist-info/RECORD
