Metadata-Version: 2.1
Name: storageprovider-client
Version: 2.6.0
Summary: storageprovider client
Home-page: http://www.onroerenderfgoed.be
Author: Flanders Heritage Agency
Author-email: ict@onroerenderfgoed.be
License: MIT
Keywords: storageprovider client
Platform: UNKNOWN
Classifier: Programming Language :: Python
Classifier: Topic :: Internet :: WWW/HTTP
Requires-Dist: requests
